estipy/__init__.py
estipy-0.0.4.dist-info/LICENSE
estipy-0.0.4.dist-info/METADATA
estipy-0.0.4.dist-info/WHEEL
estipy-0.0.4.dist-info/top_level.txt
estipy-0.0.4.dist-info/RECORD
