Metadata-Version: 2.1
Name: estipy
Version: 0.0.4
Summary: Estimated time of availability calculator
Home-page: https://github.com/linuskmr/estipy
Author: linuskmr
Author-email: linuskmr.dev@gmail.com
License: UNKNOWN
Project-URL: Bug Tracker, https://github.com/linuskmr/estipy/issues
Platform: UNKNOWN
Classifier: Programming Language :: Python :: 3
Classifier: License :: OSI Approved :: MIT License
Classifier: Operating System :: OS Independent
Requires-Python: >=3.6
License-File: LICENSE
